.
setup.py
./bin/archivedb
/
archivedb/__init__.py
archivedb/common.py
archivedb/config.py
archivedb/core.py
archivedb/logger.py
archivedb/monitor.py
archivedb/sql.py
archivedb/threads.py
archivedb.egg-info/PKG-INFO
archivedb.egg-info/SOURCES.txt
archivedb.egg-info/dependency_links.txt
archivedb.egg-info/requires.txt
archivedb.egg-info/top_level.txt
archivedb/plugins/__init__.py
archivedb/plugins/imdb.py