Metadata-Version: 1.0
Name: archivedb
Version: 0.2.3
Summary: A utility that maintains a checksum database of your media archive
Home-page: https://github.com/cjlucas/archivedb
Author: Chris Lucas
Author-email: chris@chrisjlucas.com
License: MIT
Platform: UNKNOWN
Classifier: Development Status :: 4 - Beta
Classifier: Intended Audience :: End Users/Desktop
Classifier: Natural Language :: English
Classifier: License :: OSI Approved :: MIT License
Classifier: Operating System :: MacOS
Classifier: Operating System :: POSIX :: Linux
Classifier: Programming Language :: Python :: 2
Classifier: Programming Language :: Python :: 3
Classifier: Topic :: Database
Classifier: Topic :: System :: Archiving
